line_item_manager/__init__.py
line_item_manager/cli.py
line_item_manager/config.py
line_item_manager/exceptions.py
line_item_manager/gam_config.py
line_item_manager/gam_operations.py
line_item_manager/operations.py
line_item_manager/prebid.py
line_item_manager/template.py
line_item_manager/utils.py
line_item_manager/validate.py
line_item_manager/yaml_date.py
line_item_manager/conf.d/googleads.yaml
line_item_manager/conf.d/line_item_manager.yml
line_item_manager/conf.d/line_item_template.yml
line_item_manager/conf.d/schema.yml
line_item_manager/conf.d/settings.yml
line_item_manager-0.2.14.dist-info/licenses/AUTHORS.rst
line_item_manager-0.2.14.dist-info/licenses/LICENSE
line_item_manager-0.2.14.dist-info/METADATA
line_item_manager-0.2.14.dist-info/WHEEL
line_item_manager-0.2.14.dist-info/entry_points.txt
line_item_manager-0.2.14.dist-info/top_level.txt
line_item_manager-0.2.14.dist-info/RECORD
