Metadata-Version: 2.4
Name: line-item-manager
Version: 0.2.14
Summary: Create and manage line items.
Home-page: https://github.com/prebid/line-item-manager
Author: the prebid contributors
Author-email: info@prebid.org
License: Apache Software License 2.0
Keywords: line-item-manager
Classifier: Development Status :: 4 - Beta
Classifier: Intended Audience :: Developers
Classifier: License :: OSI Approved :: Apache Software License
Classifier: Natural Language :: English
Classifier: Programming Language :: Python :: 3
Classifier: Programming Language :: Python :: 3.8
Classifier: Programming Language :: Python :: 3.9
Classifier: Programming Language :: Python :: 3.10
Classifier: Programming Language :: Python :: 3.11
Requires-Python: >=3.8
License-File: LICENSE
License-File: AUTHORS.rst
Requires-Dist: Click==8.1.7
Requires-Dist: googleads==47.0.0
Requires-Dist: jinja2==3.0.3
Requires-Dist: jsonschema==4.23.0
Requires-Dist: PyYAML==6.0.1
Requires-Dist: retrying==1.3.3
Requires-Dist: tqdm==4.56.0
Provides-Extra: release
Requires-Dist: bump2version>=1; extra == "release"
Requires-Dist: twine>=5; extra == "release"
Provides-Extra: test
Requires-Dist: flake8==3.8.4; extra == "test"
Requires-Dist: mock==4.0.2; extra == "test"
Requires-Dist: pytest==7.0.0; extra == "test"
Requires-Dist: pytest-cov==3.0.0; extra == "test"
Requires-Dist: pytest-runner==5.3.1; extra == "test"
Dynamic: author
Dynamic: author-email
Dynamic: classifier
Dynamic: description
Dynamic: home-page
Dynamic: keywords
Dynamic: license
Dynamic: license-file
Dynamic: provides-extra
Dynamic: requires-dist
Dynamic: requires-python
Dynamic: summary
